crypto_mcp/__init__.py
crypto_mcp/__main__.py
crypto_mcp/crypto_mcp.py
crypto_mcp-0.1.6.dist-info/licenses/LICENSE
crypto_mcp-0.1.6.dist-info/METADATA
crypto_mcp-0.1.6.dist-info/WHEEL
crypto_mcp-0.1.6.dist-info/entry_points.txt
crypto_mcp-0.1.6.dist-info/top_level.txt
crypto_mcp-0.1.6.dist-info/RECORD
